nytid/Makefile
nytid/__init__.py
nytid/cli/Makefile
nytid/cli/__init__.py
nytid/cli/courses.nw
nytid/cli/courses.py
nytid/cli/hr.nw
nytid/cli/hr.py
nytid/cli/init.nw
nytid/cli/schedule.nw
nytid/cli/schedule.py
nytid/cli/signupsheets.nw
nytid/cli/signupsheets.py
nytid/cli/track.nw
nytid/cli/track.py
nytid/cli/utils/Makefile
nytid/cli/utils/__init__.py
nytid/cli/utils/init.nw
nytid/cli/utils/rooms.nw
nytid/cli/utils/rooms.py
nytid/courses/Makefile
nytid/courses/__init__.py
nytid/courses/init.nw
nytid/courses/registry.nw
nytid/courses/registry.py
nytid/http_utils.nw
nytid/http_utils.py
nytid/httputils.py
nytid/schedules.crap/__init__.py
nytid/schedules.crap/utils.py
nytid/schedules.nw
nytid/schedules.py
nytid/signup/Makefile
nytid/signup/__init__.py
nytid/signup/hr/Makefile
nytid/signup/hr/__init__.py
nytid/signup/hr/hr.nw
nytid/signup/hr/timesheet/Makefile
nytid/signup/hr/timesheet/README.md
nytid/signup/hr/timesheet/__init__.py
nytid/signup/hr/timesheet/kth.png
nytid/signup/hr/timesheet/screen_shot.png
nytid/signup/hr/timesheet/signature.png
nytid/signup/sheets.nw
nytid/signup/sheets.py
nytid/signup/utils.nw
nytid/signup/utils.py
nytid/storage/Makefile
nytid/storage/__init__.py
nytid/storage/afs.nw
nytid/storage/afs.py
nytid/storage/init.nw
nytid-9.10.dist-info/METADATA
nytid-9.10.dist-info/WHEEL
nytid-9.10.dist-info/entry_points.txt
nytid-9.10.dist-info/licenses/LICENSE
nytid-9.10.dist-info/RECORD
